sonorapy/__init__.py
sonorapy/analysis.py
sonorapy/calc.py
sonorapy/common.py
sonorapy/consts.py
sonorapy/h5.py
sonorapy/io.py
sonorapy/solver.py
sonorapy/utils.py
sonorapy/viz.py
sonorapy/acoustics/__init__.py
sonorapy/acoustics/analysis.py
sonorapy/acoustics/ground_effect.py
sonorapy/acoustics/impedance.py
sonorapy/discretization/__init__.py
sonorapy/discretization/atlas.py
sonorapy/discretization/discretization.py
sonorapy/math/__init__.py
sonorapy/math/frequency.py
sonorapy/math/interpolation.py
sonorapy/math/octave_band.py
sonorapy-0.1.0.dist-info/licenses/LICENSE
sonorapy-0.1.0.dist-info/METADATA
sonorapy-0.1.0.dist-info/WHEEL
sonorapy-0.1.0.dist-info/top_level.txt
sonorapy-0.1.0.dist-info/RECORD
