Metadata-Version: 2.4
Name: sonorapy
Version: 0.1.0
Summary: Python interface for 3D GPU-accelerated acoustics FDTD solver Sonora
Author-email: Hazael Montanaro <hazael.montanaro@empa.ch>
License-Expression: LicenseRef-Proprietary
Classifier: Programming Language :: Python :: 3
Classifier: Operating System :: OS Independent
Requires-Python: >=3.9
License-File: LICENSE
Requires-Dist: numpy
Requires-Dist: scipy
Requires-Dist: matplotlib
Requires-Dist: pandas
Requires-Dist: h5py
Requires-Dist: vtk
Requires-Dist: trimesh[easy]
Dynamic: license-file
